<reports>
<report>
<year>1952</year>
<rawcontent>
<![CDATA[52/M7
WHEAT - WOBURN STACKYARD 1952

For history, details of treatments etc., see "Results of the Field
Experiments 1939-47".

Cultivations, etc.: Ploughed: Sept 4, 1951. Seed drilled at 3 bushels
per acre: Oct 20. Nitrochalk applied: Apr 23, 1952. Sprayed with
D.N.0.C. 2/3 gallon per acre: May 19 and again May 23. Harvested:
July 29, Variety: Squarehcads Master (13/1).

Summary of Results
Nitrochelk
dressing Grain: Straw:
Flot cwt per acre cwt per acre owt per acre

3 2 3.2 8.5
1 L 7.0 22.7
7 6 L.8 13.9
6 2 h2 1.3
9 4 7.7 18.6
4 6 8.6 25.3
110 (2 2 6.1 13.5
11b (3 L 9.3 21.4
11d (1 6. 13.6 25.2
11a 2 3.9 13.0
10a L 6.5 18.4
10b 6 7.0 16.8
]]></rawcontent>
</report>
<report>
<year>1953</year>
<rawcontent>
<![CDATA[53/L/T
WHEAT - WOBURN STACKY.RD 1953

For history, details of treatments etc., see "Results of the Field
Experiments 1939-47" Vol I, Scction L/7.

Cultivations, etcs: Floughcd: Aug 27, 1952. Seed drilled at 3
bushels per acre: Oct 10, Nitrochalk applied: Lpr 20, 1953.
Sprayed with DNOC 6 1b in 80 gallons: May 22, Harvested: Aug 18.
Variety: Squarch:ads Master (13/4).

Summary of Results
Nitrochalk

dressing Grain: Straw:

Plot cwt pcr acre cwt per acre cwt per acre
1 2 749 16.0
7 4 10.1 20.8
3 6 | 13.8 21.6
5 2 | Tal 15,8
kL Le 12.1 2349
6 6 17.9 27.8
11d (3) 2 749 15.9
11 (1 4 | 13.8 24.2
110 (2 6 17.1 26.9
10a 2 76 14.2
10b 4 10.2 19.2
11a 6 i 177 2L.6
]]></rawcontent>
</report>
<report>
<year>1954</year>
<rawcontent>
<![CDATA[|
5/4/17
HEAT - FOBURN STACKYARD 1954 |
For history, details of treatments etc., see "Results of the Field |
Experiments 1939-47" Vol. I, Section 4/7.
Cultivations, etc.: Ploughed: Sept 17, 1953. Seed drilled at
3 bushels per acre: Oct 23. Sprayed with D,N.0.C. 6 1b per acre in
80 gals. : Apr 27, 1954.  Nitrochalk applied: Apr 28. Sprayed with
2; 4-D, 2 pints per acre at low volume: May 14. Harvested: Sept 8.
Variety: Squareheads Master 13/L.
Summary of Results
Nitrochalk |
dressing Grain: Straw:
Flot cwt per acre | cwt per acre cwt per acre
7 2 5.7 2s |
3 L 6.6 8.9
1 6 7.5 14.1
|
4 2 8.8 8.3 |
6 4 12.4 10.0
9 6 15.8 13.7
11b(1 2 15.3 23.6
11b(2 4 16.6 24.6
110(3 6 18.9 31.0
10b 2 3.3 3.5
11a L 8.0 8.1
10a 6 6.8 11.6
]]></rawcontent>
</report>
<report>
<year>1955</year>
<rawcontent>
<![CDATA[55/M17
WHEAT - WOBURN STACKYARD 1955

For history, details of treatments etc., see "Results of the Field
Experiments" 1939-47, Vol. I, Section 4/7.

In 1955 dressings of calcium carbonate were applied ranging from 20
to 50 cwt per acre according to the acidity of the plots, which
were bare fallowed.

Cultivations, etc.: Ploughed: Nov 2, 1954. First dressing of ground
chalk applied: Feb 15, 1955. Second dressing of ground chalk
applied: Mar 8. Ploughed: Mar 17. Third dressing of ground
chalk applied: Apr 16,  Ploughed: May 6; Aug 2; Sept 26.
]]></rawcontent>
</report>
<report>
<year>1956</year>
<rawcontent>
<![CDATA[56/4/8
WHEAT . AND BARLEY - WOBUKN STACKYARD 1956

For history, treatments etc., for both experiments see "Details of the
Classicel and Long Term Experiments" 1956.

The land was bare fallowed in 1956 and sprayed with TCA (trichloracetic acid)
to control grasses (Holcus mollis 4% posse gigantea). The two halvés of
each plot were sprayed separctely at ‘eren + Ground chalk
was applied to certain areas at 7.5 and 15 cwt Calo per acre.

A s0il survey of the experimental area was made.

Cultivations etcs: Wheat
Ploughed: Sept 26, 1955. Half of each plot sprayed with TCA, 20 1b

in 40 gallons per acre: Nov 30, 1955 and again Mar 28, 1956.
Floughed across plots: June 18 - 20. Remaining half plots
sprayed with TCA at 20 1b in 40 gallons per acre: July 26 and
again Sept 26. Ground chalk applied: Aug 15.
Barley
Ploughed: Sept 7 - 25, 1955. Half of each plot sprayed with TCA,
20 1b in LO gallons per acre: Dec 1, 1955 and again on Mar 28, 1956.
Floughed across plots: June 18 - 20. Remaining half plots
sprayed with TCA at 20 1b in 40 gallons per acre: July 25 and
again Sept 26, Ground chalk applied: Aug 15.
]]></rawcontent>
</report>
<report>
<year>1957</year>
<rawcontent>
<![CDATA[51/48
WHEAT AND BARLEY - 7OBURN STACKYARD 1957
For history, treatments, ctc., for both experiments see "Details of
the Classical and Long Term Experiments" 1956.
The land was bare fallowed in 1957. Ground chalk wasgplied to
certain areas at 7.5 and 15 ct CaCO; per acre.
Cultivations, ete. :
Wheat and Barley
Floughed three times: Nov 20, 1956, Apr 16, 1957, July 29. Ground
chalk applied: Aug 8.
]]></rawcontent>
</report>
<report>
<year>1958</year>
<rawcontent>
<![CDATA[58/4/8
WHEAT - WOBURN ST..CKL.KD 1958

For history, treatments, ctc., sce "Details of the Classicel and Long
Term Experiments” 1956.

On account of poor development, perticularly of the winter sown crovs,
it was decided to plough out the whole arca of this cxperiment on
May 28, 1958.

Cultivetions, etc.: Floughed: Nov 20, 1956, «pr 16, and July 23, 1957.
Ground chalk applied: aug 8. ‘Winter sown whet and barley drilled:
Nov 19, Spring sown wheat and barley drilled: Mar 21, 1958.
Varisties: Winter sown whert - Squarchoad's liaster 13/4; spring
sown whoat - Peko; winter sown barley - Pioneer; spring sown
barley = Plumage ixrchor.

BARLEY - WOBURN STU.CKY..RD 1958

For history, treatments, etc., sce "Deteils of the Classicel and Long
Term Sxperimonts" 1956.

On account of poor devulopment, particlarly of the winter sown crops,
it was decided to plough out the whole arca of this experiment on
May 27, 1956.

Cultivations, etc.: Floughed: Nov 21, 1956, ipr 17, and July 30, 1357.

: Ground cnelk applied: .ug 8, #inter sown wheat and barley drilled:
Nov 19. Spring sown wheat and barley drilled: Mar 21, 1358.
Vericties: Winter sown wheat — Squarehcad's Mastor 13/4; spring sown
wheat - Peko; winter sown borley - Ploncer; spring sown berley =
Plumage :ixchor. »
]]></rawcontent>
</report>
</reports>